Perseus/__init__.py
Perseus/_perseus.cpython-39-darwin.so
Perseus2-4.0.1.dist-info/LICENSE
Perseus2-4.0.1.dist-info/METADATA
Perseus2-4.0.1.dist-info/WHEEL
Perseus2-4.0.1.dist-info/top_level.txt
Perseus2-4.0.1.dist-info/RECORD
