Metadata-Version: 2.1
Name: Perseus2
Version: 4.0.1
Summary: Perseus Software for Persistent Homology Computation
Home-page: https://github.com/marciogameiro/Perseus
Author: Marcio Gameiro
Author-email: marciogameiro@gmail.com
License: UNKNOWN
Platform: UNKNOWN
License-File: LICENSE
